oddments/__init__.py
oddments/iteration/__init__.py
oddments/iteration/utils.py
oddments/pandas/__init__.py
oddments/pandas/coercion/__init__.py
oddments/pandas/coercion/decorators.py
oddments/pandas/coercion/utils.py
oddments/pandas/combine.py
oddments/pandas/decorators.py
oddments/pandas/dropna.py
oddments/pandas/dupes.py
oddments/pandas/indexing/__init__.py
oddments/pandas/indexing/utils.py
oddments/pandas/indexing/validation.py
oddments/pandas/utils.py
oddments/sorting/__init__.py
oddments/sorting/natural.py
oddments/text/__init__.py
oddments/text/utils.py
oddments/validation/__init__.py
oddments/validation/decorators.py
oddments/validation/utils.py
oddments-0.5.0.dist-info/LICENSE
oddments-0.5.0.dist-info/METADATA
oddments-0.5.0.dist-info/WHEEL
oddments-0.5.0.dist-info/RECORD
