Metadata-Version: 2.1
Name: oddments
Version: 0.5.0
Summary: Collection of general-purpose utilities.
Home-page: https://github.com/zteinck/oddments
License: MIT
Author: Zachary Einck
Author-email: zacharyeinck@gmail.com
Requires-Python: >=3.8,<4.0
Classifier: License :: OSI Approved :: MIT License
Classifier: Programming Language :: Python :: 3
Classifier: Programming Language :: Python :: 3.8
Classifier: Programming Language :: Python :: 3.9
Classifier: Programming Language :: Python :: 3.10
Classifier: Programming Language :: Python :: 3.11
Classifier: Programming Language :: Python :: 3.12
Requires-Dist: numpy
Requires-Dist: pandas
Project-URL: Repository, https://github.com/zteinck/oddments
